[
  {
    "content_id": 341199,
    "reference_id": 186601,
    "title": "apostle",
    "media_type": "Audio",
    "index_reference": "apostle",
    "language": "eng",
    "content": "<h3>Audio Content</h3>\n",
    "associations": {
      "passage": [
        {
          "start_ref": "44008004",
          "start_ref_usfm": "ACT 8:4",
          "end_ref": "44008025",
          "end_ref_usfm": "ACT 8:25"
        },
        {
          "start_ref": "44009019",
          "start_ref_usfm": "ACT 9:19",
          "end_ref": "44009031",
          "end_ref_usfm": "ACT 9:31"
        },
        {
          "start_ref": "44011001",
          "start_ref_usfm": "ACT 11:1",
          "end_ref": "44011018",
          "end_ref_usfm": "ACT 11:18"
        },
        {
          "start_ref": "44012001",
          "start_ref_usfm": "ACT 12:1",
          "end_ref": "44012005",
          "end_ref_usfm": "ACT 12:5"
        },
        {
          "start_ref": "44014008",
          "start_ref_usfm": "ACT 14:8",
          "end_ref": "44014020",
          "end_ref_usfm": "ACT 14:20"
        },
        {
          "start_ref": "42006012",
          "start_ref_usfm": "LUK 6:12",
          "end_ref": "42006016",
          "end_ref_usfm": "LUK 6:16"
        },
        {
          "start_ref": "42017001",
          "start_ref_usfm": "LUK 17:1",
          "end_ref": "42017010",
          "end_ref_usfm": "LUK 17:10"
        },
        {
          "start_ref": "40010001",
          "start_ref_usfm": "MAT 10:1",
          "end_ref": "40010015",
          "end_ref_usfm": "MAT 10:15"
        },
        {
          "start_ref": "41003013",
          "start_ref_usfm": "MRK 3:13",
          "end_ref": "41003019",
          "end_ref_usfm": "MRK 3:19"
        },
        {
          "start_ref": "41006030",
          "start_ref_usfm": "MRK 6:30",
          "end_ref": "41006044",
          "end_ref_usfm": "MRK 6:44"
        },
        {
          "start_ref": "44004032",
          "start_ref_usfm": "ACT 4:32",
          "end_ref": "44004037",
          "end_ref_usfm": "ACT 4:37"
        },
        {
          "start_ref": "44014001",
          "start_ref_usfm": "ACT 14:1",
          "end_ref": "44014007",
          "end_ref_usfm": "ACT 14:7"
        },
        {
          "start_ref": "44016001",
          "start_ref_usfm": "ACT 16:1",
          "end_ref": "44016005",
          "end_ref_usfm": "ACT 16:5"
        },
        {
          "start_ref": "44006001",
          "start_ref_usfm": "ACT 6:1",
          "end_ref": "44006007",
          "end_ref_usfm": "ACT 6:7"
        },
        {
          "start_ref": "44004001",
          "start_ref_usfm": "ACT 4:1",
          "end_ref": "44004022",
          "end_ref_usfm": "ACT 4:22"
        },
        {
          "start_ref": "44005001",
          "start_ref_usfm": "ACT 5:1",
          "end_ref": "44005011",
          "end_ref_usfm": "ACT 5:11"
        },
        {
          "start_ref": "44005012",
          "start_ref_usfm": "ACT 5:12",
          "end_ref": "44005016",
          "end_ref_usfm": "ACT 5:16"
        },
        {
          "start_ref": "42024001",
          "start_ref_usfm": "LUK 24:1",
          "end_ref": "42024012",
          "end_ref_usfm": "LUK 24:12"
        },
        {
          "start_ref": "44002037",
          "start_ref_usfm": "ACT 2:37",
          "end_ref": "44002041",
          "end_ref_usfm": "ACT 2:41"
        },
        {
          "start_ref": "44005017",
          "start_ref_usfm": "ACT 5:17",
          "end_ref": "44005026",
          "end_ref_usfm": "ACT 5:26"
        },
        {
          "start_ref": "44002041",
          "start_ref_usfm": "ACT 2:41",
          "end_ref": "44002047",
          "end_ref_usfm": "ACT 2:47"
        },
        {
          "start_ref": "44005027",
          "start_ref_usfm": "ACT 5:27",
          "end_ref": "44005042",
          "end_ref_usfm": "ACT 5:42"
        },
        {
          "start_ref": "44001015",
          "start_ref_usfm": "ACT 1:15",
          "end_ref": "44001026",
          "end_ref_usfm": "ACT 1:26"
        },
        {
          "start_ref": "44001001",
          "start_ref_usfm": "ACT 1:1",
          "end_ref": "44001005",
          "end_ref_usfm": "ACT 1:5"
        },
        {
          "start_ref": "42009001",
          "start_ref_usfm": "LUK 9:1",
          "end_ref": "42009017",
          "end_ref_usfm": "LUK 9:17"
        },
        {
          "start_ref": "44007054",
          "start_ref_usfm": "ACT 7:54",
          "end_ref": "44008003",
          "end_ref_usfm": "ACT 8:3"
        },
        {
          "start_ref": "44015022",
          "start_ref_usfm": "ACT 15:22",
          "end_ref": "44015035",
          "end_ref_usfm": "ACT 15:35"
        },
        {
          "start_ref": "42011033",
          "start_ref_usfm": "LUK 11:33",
          "end_ref": "42011054",
          "end_ref_usfm": "LUK 11:54"
        },
        {
          "start_ref": "42022007",
          "start_ref_usfm": "LUK 22:7",
          "end_ref": "42022023",
          "end_ref_usfm": "LUK 22:23"
        }
      ],
      "resource": [
        {
          "reference_id": 186517,
          "content_id": 280097,
          "resource_code": "Unknown",
          "label": "miracles",
          "language": "eng"
        },
        {
          "reference_id": 186517,
          "content_id": 341100,
          "resource_code": "Unknown",
          "label": "miracles",
          "language": "eng"
        },
        {
          "reference_id": 186552,
          "content_id": 280132,
          "resource_code": "Unknown",
          "label": "gospel",
          "language": "eng"
        },
        {
          "reference_id": 186630,
          "content_id": 280210,
          "resource_code": "Unknown",
          "label": "disciple",
          "language": "eng"
        },
        {
          "reference_id": 186552,
          "content_id": 341139,
          "resource_code": "Unknown",
          "label": "gospel",
          "language": "eng"
        },
        {
          "reference_id": 186630,
          "content_id": 341232,
          "resource_code": "Unknown",
          "label": "disciple",
          "language": "eng"
        }
      ]
    }
  }
]