[
  {
    "content_id": 341061,
    "reference_id": 186788,
    "version": "1.0.0",
    "title": "Hebron",
    "media_type": "Audio",
    "index_reference": "hebron",
    "language": "eng",
    "content": "<h3>Audio Content</h3>\n",
    "associations": {
      "passage": [
        {
          "start_ref": "01023001",
          "start_ref_usfm": "GEN 23:1",
          "end_ref": "01023020",
          "end_ref_usfm": "GEN 23:20"
        }
      ],
      "resource": [
        {
          "reference_id": 186466,
          "content_id": 280046,
          "resource_code": "Unknown",
          "label": "David",
          "language": "eng"
        },
        {
          "reference_id": 186466,
          "content_id": 341041,
          "resource_code": "Unknown",
          "label": "David",
          "language": "eng"
        },
        {
          "reference_id": 186523,
          "content_id": 280103,
          "resource_code": "Unknown",
          "label": "Jerusalem",
          "language": "eng"
        },
        {
          "reference_id": 186562,
          "content_id": 280142,
          "resource_code": "Unknown",
          "label": "Israelite",
          "language": "eng"
        },
        {
          "reference_id": 186523,
          "content_id": 341106,
          "resource_code": "Unknown",
          "label": "Jerusalem",
          "language": "eng"
        },
        {
          "reference_id": 186562,
          "content_id": 341150,
          "resource_code": "Unknown",
          "label": "Israelite",
          "language": "eng"
        },
        {
          "reference_id": 186621,
          "content_id": 280201,
          "resource_code": "Unknown",
          "label": "Abraham",
          "language": "eng"
        },
        {
          "reference_id": 186627,
          "content_id": 280207,
          "resource_code": "Unknown",
          "label": "Israel",
          "language": "eng"
        },
        {
          "reference_id": 186796,
          "content_id": 341020,
          "resource_code": "Unknown",
          "label": "king",
          "language": "eng"
        },
        {
          "reference_id": 186796,
          "content_id": 341119,
          "resource_code": "Unknown",
          "label": "king",
          "language": "eng"
        },
        {
          "reference_id": 186621,
          "content_id": 341221,
          "resource_code": "Unknown",
          "label": "Abraham",
          "language": "eng"
        },
        {
          "reference_id": 186627,
          "content_id": 341229,
          "resource_code": "Unknown",
          "label": "Israel",
          "language": "eng"
        }
      ]
    }
  }
]