[
  {
    "content_id": 341111,
    "reference_id": 186794,
    "title": "pharaoh",
    "media_type": "Audio",
    "index_reference": "pharaoh",
    "language": "eng",
    "content": "<h3>Audio Content</h3>\n",
    "associations": {
      "passage": [
        {
          "start_ref": "01012010",
          "start_ref_usfm": "GEN 12:10",
          "end_ref": "01012020",
          "end_ref_usfm": "GEN 12:20"
        },
        {
          "start_ref": "02010021",
          "start_ref_usfm": "EXO 10:21",
          "end_ref": "02010029",
          "end_ref_usfm": "EXO 10:29"
        },
        {
          "start_ref": "02002016",
          "start_ref_usfm": "EXO 2:16",
          "end_ref": "02002025",
          "end_ref_usfm": "EXO 2:25"
        },
        {
          "start_ref": "02003001",
          "start_ref_usfm": "EXO 3:1",
          "end_ref": "02003010",
          "end_ref_usfm": "EXO 3:10"
        },
        {
          "start_ref": "02007014",
          "start_ref_usfm": "EXO 7:14",
          "end_ref": "02007025",
          "end_ref_usfm": "EXO 7:25"
        },
        {
          "start_ref": "02008001",
          "start_ref_usfm": "EXO 8:1",
          "end_ref": "02008015",
          "end_ref_usfm": "EXO 8:15"
        },
        {
          "start_ref": "02008016",
          "start_ref_usfm": "EXO 8:16",
          "end_ref": "02008019",
          "end_ref_usfm": "EXO 8:19"
        },
        {
          "start_ref": "02008020",
          "start_ref_usfm": "EXO 8:20",
          "end_ref": "02008032",
          "end_ref_usfm": "EXO 8:32"
        },
        {
          "start_ref": "02009001",
          "start_ref_usfm": "EXO 9:1",
          "end_ref": "02009007",
          "end_ref_usfm": "EXO 9:7"
        },
        {
          "start_ref": "02009008",
          "start_ref_usfm": "EXO 9:8",
          "end_ref": "02009012",
          "end_ref_usfm": "EXO 9:12"
        },
        {
          "start_ref": "02009013",
          "start_ref_usfm": "EXO 9:13",
          "end_ref": "02009021",
          "end_ref_usfm": "EXO 9:21"
        },
        {
          "start_ref": "02014001",
          "start_ref_usfm": "EXO 14:1",
          "end_ref": "02014014",
          "end_ref_usfm": "EXO 14:14"
        },
        {
          "start_ref": "02006028",
          "start_ref_usfm": "EXO 6:28",
          "end_ref": "02007013",
          "end_ref_usfm": "EXO 7:13"
        },
        {
          "start_ref": "02004018",
          "start_ref_usfm": "EXO 4:18",
          "end_ref": "02004031",
          "end_ref_usfm": "EXO 4:31"
        },
        {
          "start_ref": "02022025",
          "start_ref_usfm": "EXO 22:25",
          "end_ref": "02022031",
          "end_ref_usfm": "EXO 22:31"
        },
        {
          "start_ref": "02003011",
          "start_ref_usfm": "EXO 3:11",
          "end_ref": "02003022",
          "end_ref_usfm": "EXO 3:22"
        },
        {
          "start_ref": "02012029",
          "start_ref_usfm": "EXO 12:29",
          "end_ref": "02012042",
          "end_ref_usfm": "EXO 12:42"
        },
        {
          "start_ref": "02015019",
          "start_ref_usfm": "EXO 15:19",
          "end_ref": "02015027",
          "end_ref_usfm": "EXO 15:27"
        },
        {
          "start_ref": "02005022",
          "start_ref_usfm": "EXO 5:22",
          "end_ref": "02006013",
          "end_ref_usfm": "EXO 6:13"
        },
        {
          "start_ref": "02001008",
          "start_ref_usfm": "EXO 1:8",
          "end_ref": "02001014",
          "end_ref_usfm": "EXO 1:14"
        },
        {
          "start_ref": "02006014",
          "start_ref_usfm": "EXO 6:14",
          "end_ref": "02006027",
          "end_ref_usfm": "EXO 6:27"
        },
        {
          "start_ref": "02013017",
          "start_ref_usfm": "EXO 13:17",
          "end_ref": "02013022",
          "end_ref_usfm": "EXO 13:22"
        },
        {
          "start_ref": "02011001",
          "start_ref_usfm": "EXO 11:1",
          "end_ref": "02011010",
          "end_ref_usfm": "EXO 11:10"
        },
        {
          "start_ref": "02005001",
          "start_ref_usfm": "EXO 5:1",
          "end_ref": "02005021",
          "end_ref_usfm": "EXO 5:21"
        },
        {
          "start_ref": "02002001",
          "start_ref_usfm": "EXO 2:1",
          "end_ref": "02002010",
          "end_ref_usfm": "EXO 2:10"
        },
        {
          "start_ref": "02001015",
          "start_ref_usfm": "EXO 1:15",
          "end_ref": "02001022",
          "end_ref_usfm": "EXO 1:22"
        }
      ],
      "resource": [
        {
          "reference_id": 186796,
          "content_id": 341020,
          "resource_code": "Unknown",
          "label": "king",
          "language": "eng"
        },
        {
          "reference_id": 186796,
          "content_id": 341119,
          "resource_code": "Unknown",
          "label": "king",
          "language": "eng"
        }
      ]
    }
  }
]