[
  {
    "content_id": 280095,
    "reference_id": 186515,
    "title": "inn",
    "media_type": "Text",
    "index_reference": "inn",
    "language": "eng",
    "content": "<p>An <strong>inn</strong> is a general term for a place where travelers can stay. This could be a place where people had to pay some money so that they could stay there, but often it meant a room in someone&apos;s house that was reserved for guests. When relatives or friends came to visit, they could stay in this room.</p>",
    "associations": {
      "passage": [
        {
          "start_ref": "42002001",
          "start_ref_usfm": "LUK 2:1",
          "end_ref": "42002021",
          "end_ref_usfm": "LUK 2:21"
        },
        {
          "start_ref": "42010025",
          "start_ref_usfm": "LUK 10:25",
          "end_ref": "42010037",
          "end_ref_usfm": "LUK 10:37"
        }
      ],
      "resource": []
    }
  }
]